[
    

    {
        "id": "1",
        "name": "Apple Investment",
        "symbol": "AAPL",
        "type": "Stock",
        "purchase": {
            "date": "2023-03-29T22:00:00.000Z",
            "amount": 10,
            "price": 171.5
        },
        "historicalData": "AAPL"
    },
    {
        "id": "2",
        "name": "i dont know what this is",
        "symbol": "ZWS",
        "type": "Stock",
        "purchase": {
            "date": "2023-04-29T22:00:00.000Z",
            "amount": 20,
            "price": 21.44
        },
        "historicalData": "ZWS"
    },
    {
        "id": "3",
        "name": "Tesla Fan Boyyyyyyyyy",
        "symbol": "TSLA",
        "type": "Stock",
        "purchase": {
            "date": "2023-02-28T22:00:00.000Z",
            "amount": 5,
            "price": 147.41
        },
        "historicalData": "TSLA"
    },
    {
        "id": "4",
        "name": "Bitcoin",
        "symbol": "BTC",
        "type": "Crypto",
        "purchase": {
            "date": "2023-01-29T22:00:00.000Z",
            "amount": 0.05,
            "price": 50000
        },
        "historicalData": [
            {
                "date": "2023-01-29T22:00:00.000Z",
                "value": 50000
            },
            {
                "date": "2023-02-29T22:00:00.000Z",
                "value": 60000
            },
            {
                "date": "2023-03-29T22:00:00.000Z",
                "value": 70000
            },
            {
                "date": "2023-04-29T22:00:00.000Z",
                "value": 80000
            }
        ]
    },
        {
        "id": "1",
        "name": "Apple Investment",
        "symbol": "AAPL",
        "type": "Stock",
        "purchase": {
            "date": "2023-03-29T22:00:00.000Z",
            "amount": 10,
            "price": 171.5
        },
        "historicalData": "AAPL"
    }
]